{"name":"Post Recommendations for WordPress","body":"Post Recommendations for WordPress\r\n==================================\r\n\r\njQuery-powered recommendations. \r\n\r\n\r\nHow to use:\r\n\r\nPut this code in a **single.php** page, or anywhere you want. \r\n\r\n```php\r\n$args = array(); \r\nwp_recommendations($args); \r\n```\r\n\r\nHere are the options: \r\n\r\n```php\r\n$defaults = array( \r\n\t'postID' => $post->ID,\r\n\t'size' => null,  \r\n\t'numberposts' => 6, \r\n\t'orderby' => 'rand', \r\n\t'show' => TRUE\r\n); \r\n```\r\n","tagline":"jQuery-powered recommendations. ","google":"","note":"Don't delete this file! It's used internally to help with page regeneration."}